combinational/mux_4to1.v
module mux_4to1 (
    input  I0,
    input  I1,
    input  I2,
    input  I3,
    input  S0,
    input  S1,
    output Y
);

    assign Y = (~S1 & ~S0 & I0) |
               (~S1 &  S0 & I1) |
               ( S1 & ~S0 & I2) |
               ( S1 &  S0 & I3);

endmodule

simulation/4_to_1_mux/mux_4to1_tb.v
`timescale 1ns/1ps

module mux_4to1_tb;

    reg I0, I1, I2, I3;
    reg S0, S1;
    wire Y;

    // Instantiate the 4-to-1 MUX
    mux_4to1 uut (
        .I0(I0),
        .I1(I1),
        .I2(I2),
        .I3(I3),
        .S0(S0),
        .S1(S1),
        .Y(Y)
    );

    initial begin

        // Create waveform file
        $dumpfile("mux_4to1.vcd");
        $dumpvars(0, mux_4to1_tb);

        // Display results
        $monitor("Time=%0t | I0=%b I1=%b I2=%b I3=%b | S1=%b S0=%b | Y=%b",
                 $time, I0, I1, I2, I3, S1, S0, Y);

        // Input values
        I0 = 0;
        I1 = 1;
        I2 = 0;
        I3 = 1;

        // S1 S0 = 00 -> I0
        S1 = 0; S0 = 0;
        #10;

        // S1 S0 = 01 -> I1
        S1 = 0; S0 = 1;
        #10;

        // S1 S0 = 10 -> I2
        S1 = 1; S0 = 0;
        #10;

        // S1 S0 = 11 -> I3
        S1 = 1; S0 = 1;
        #10;

        // Change input values
        I0 = 1;
        I1 = 0;
        I2 = 1;
        I3 = 0;

        // Test all selections again
        S1 = 0; S0 = 0;
        #10;

        S1 = 0; S0 = 1;
        #10;

        S1 = 1; S0 = 0;
        #10;

        S1 = 1; S0 = 1;
        #10;

        $finish;
    end

endmodule

simulation/4to1mux/mux_4to1.vcd
$date
	Tue Sep 29 23:40:22 2026
$end
$version
	Icarus Verilog
$end
$timescale
	1ps
$end
$scope module mux_4to1_tb $end
$var wire 1 ! Y $end
$var reg 1 " I0 $end
$var reg 1 # I1 $end
$var reg 1 $ I2 $end
$var reg 1 % I3 $end
$var reg 1 & S0 $end
$var reg 1 ' S1 $end
$scope module uut $end
$var wire 1 " I0 $end
$var wire 1 # I1 $end
$var wire 1 $ I2 $end
$var wire 1 % I3 $end
$var wire 1 & S0 $end
$var wire 1 ' S1 $end
$var wire 1 ! Y $end
$upscope $end
$upscope $end
$enddefinitions $end
$comment Show the parameter values. $end
$dumpall
$end
#0
$dumpvars
0'
0&
1%
0$
1#
0"
0!
$end
#10000
1!
1&
#20000
0!
0&
1'
#30000
1!
1&
#40000
1!
0&
0'
0%
1$
0#
1"
#50000
0!
1&
#60000
1!
0&
1'
#70000
0!
1&
